japanese_date_input/__init__.py
japanese_date_input/frontend/build/bootstrap.min.css
japanese_date_input/frontend/build/index.html
japanese_date_input/frontend/build/assets/index-C3R9RkDn.js
japanese_date_input/frontend/build/assets/index-Crxw0sru.css
streamlit_japanese_date_input-0.1.5.dist-info/licenses/LICENSE
streamlit_japanese_date_input-0.1.5.dist-info/METADATA
streamlit_japanese_date_input-0.1.5.dist-info/WHEEL
streamlit_japanese_date_input-0.1.5.dist-info/top_level.txt
streamlit_japanese_date_input-0.1.5.dist-info/RECORD
